i3_quickterm/__init__.py
i3_quickterm/main.py
i3_quickterm-1.2.dist-info/LICENSE.txt
i3_quickterm-1.2.dist-info/METADATA
i3_quickterm-1.2.dist-info/WHEEL
i3_quickterm-1.2.dist-info/entry_points.txt
i3_quickterm-1.2.dist-info/top_level.txt
i3_quickterm-1.2.dist-info/RECORD
