Metadata-Version: 2.1
Name: i3-quickterm
Version: 1.2
Summary: A small drop-down terminal for i3 and sway
Home-page: https://github.com/lbonn/i3-quickterm
Author: lbonn
Author-email: github@lbonnans.net
Project-URL: Bug Reports, https://github.com/lbonn/i3-quickterm/issues
Project-URL: Source, https://github.com/lbonn/i3-quickterm
Keywords: i3 i3wm extensions add-ons
Classifier: Development Status :: 4 - Beta
Classifier: Intended Audience :: End Users/Desktop
Classifier: Topic :: Desktop Environment
Classifier: Topic :: Terminals :: Terminal Emulators/X Terminals
Classifier: License :: OSI Approved :: MIT License
Classifier: Programming Language :: Python :: 3
Classifier: Programming Language :: Python :: 3.8
Classifier: Programming Language :: Python :: 3.9
Classifier: Programming Language :: Python :: 3.10
Classifier: Programming Language :: Python :: 3.11
Classifier: Programming Language :: Python :: 3.12
Requires-Python: >=3.8
License-File: LICENSE.txt
Requires-Dist: i3ipc >=2.0.1
Provides-Extra: dev
Requires-Dist: black ; extra == 'dev'
Requires-Dist: coverage ; extra == 'dev'
Requires-Dist: flake8 ; extra == 'dev'
Requires-Dist: pytest ; extra == 'dev'
